{
    "stats": {
        "khach_hang": "1,520",
        "san_pham_da_ban": "480",
        "don_hang": "512",
        "doanh_thu": "1,250"
    },
    "chart_data": [
        {
            "month": "Tháng 1",
            "revenue": 150
        },
        {
            "month": "Tháng 2",
            "revenue": 230
        },
        {
            "month": "Tháng 3",
            "revenue": 180
        },
        {
            "month": "Tháng4",
            "revenue": 310
        },
        {
            "month": "Tháng5",
            "revenue": 300
        },
        {
            "month": "Tháng 6",
            "revenue": 150
        },
        {
            "month": "Tháng 7",
            "revenue": 230
        },
        {
            "month": "Tháng 8",
            "revenue": 180
        },
        {
            "month": "Tháng 9",
            "revenue": 310
        },
        {
            "month": "Tháng 10",
            "revenue": 290
        },
        {
            "month": "Tháng 11",
            "revenue": 374
        },
        {
            "month": "Tháng 12",
            "revenue": 500
        }
    ],
    "quantri": [
        {
            "id": 1,
            "name": "Nguyễn Văn A",
            "phone": "0987654321",
            "email": "vana@gmail.com",
            "total_spent": "25 tr",
            "status": "Thân thiết"
        },
        {
            "id": 3,
            "name": "Lê Văn C",
            "phone": "0911223344",
            "email": "vanc@gmail.com",
            "total_spent": "45 tr",
            "status": "VIP"
        },
        {
            "id": 3,
            "name": "Lê Hồng Mi",
            "phone": "0849941818",
            "email": "lmi313050@gmail.com",
            "total_spent": "45 tr",
            "status": "VIP"
        }
    ]
}